onapsdk/__init__.py
onapsdk/constants.py
onapsdk/exceptions.py
onapsdk/onap_service.py
onapsdk/version.py
onapsdk/aai/__init__.py
onapsdk/aai/aai_element.py
onapsdk/aai/bulk.py
onapsdk/aai/service_design_and_creation.py
onapsdk/aai/business/__init__.py
onapsdk/aai/business/customer.py
onapsdk/aai/business/instance.py
onapsdk/aai/business/line_of_business.py
onapsdk/aai/business/network.py
onapsdk/aai/business/owning_entity.py
onapsdk/aai/business/platform.py
onapsdk/aai/business/pnf.py
onapsdk/aai/business/project.py
onapsdk/aai/business/service.py
onapsdk/aai/business/sp_partner.py
onapsdk/aai/business/vf_module.py
onapsdk/aai/business/vnf.py
onapsdk/aai/cloud_infrastructure/__init__.py
onapsdk/aai/cloud_infrastructure/cloud_region.py
onapsdk/aai/cloud_infrastructure/complex.py
onapsdk/aai/cloud_infrastructure/geo_region.py
onapsdk/aai/cloud_infrastructure/tenant.py
onapsdk/aai/mixins/__init__.py
onapsdk/aai/mixins/link_to_complex.py
onapsdk/aai/mixins/link_to_geo_region.py
onapsdk/aai/mixins/link_to_project.py
onapsdk/aai/mixins/link_to_tenant.py
onapsdk/aai/network/__init__.py
onapsdk/aai/network/site_resource.py
onapsdk/aai/templates/aai_add_relationship.json.j2
onapsdk/aai/templates/aai_bulk.json.j2
onapsdk/aai/templates/aai_delete_relationship.json.j2
onapsdk/aai/templates/aai_line_of_business_create.json.j2
onapsdk/aai/templates/aai_owning_entity_create_update.json.j2
onapsdk/aai/templates/aai_platform_create.json.j2
onapsdk/aai/templates/aai_project_create.json.j2
onapsdk/aai/templates/aai_put_pnf.json.j2
onapsdk/aai/templates/aai_service_create.json.j2
onapsdk/aai/templates/aai_service_instance_create.json.j2
onapsdk/aai/templates/aai_sp_partner_create.json.j2
onapsdk/aai/templates/cloud_region_add_availability_zone.json.j2
onapsdk/aai/templates/cloud_region_add_esr_system_info.json.j2
onapsdk/aai/templates/cloud_region_add_tenant.json.j2
onapsdk/aai/templates/cloud_region_create_update.json.j2
onapsdk/aai/templates/complex_create_update.json.j2
onapsdk-14.3.0.dist-info/LICENSE
onapsdk-14.3.0.dist-info/METADATA
onapsdk-14.3.0.dist-info/WHEEL
onapsdk-14.3.0.dist-info/top_level.txt
onapsdk-14.3.0.dist-info/RECORD
