Metadata-Version: 2.1
Name: onapsdk
Version: 14.3.0
Summary: SDK to use ONAP Programatically
Home-page: https://gitlab.com/Orange-OpenSource/lfn/onap/python-onapsdk
Author: Orange OpenSource
License: Apache 2.0
Classifier: Programming Language :: Python :: 3
Classifier: Programming Language :: Python :: 3.8
Classifier: Programming Language :: Python :: 3.9
Classifier: Programming Language :: Python :: 3.10
Classifier: Programming Language :: Python :: 3.11
Requires-Python: <4,>=3.8
License-File: LICENSE
Requires-Dist: requests[socks]==2.32.3
Requires-Dist: jinja2==3.1.5
Requires-Dist: simplejson==3.17.6
Requires-Dist: oyaml==1.0
Requires-Dist: pyOpenSSL==22.0.0
Requires-Dist: jsonschema==4.4.0
Requires-Dist: dacite==1.6.0
Requires-Dist: more-itertools>=8.12.0
Requires-Dist: kafka-python-ng==2.2.2
